{
  "documentId": 56,
  "pageCount": 100,
  "images": [
    {
      "pageNumber": 1,
      "firebaseUrl": "https://firebasestorage.googleapis.com/v0/b/pdfstudy-909ca.firebasestorage.app/o/documents%2F56%2Fpage_1.png?alt=media&token=4d0c9679-088e-4726-8b4c-8f1f2cbe5cc2"
    },
    {
      "pageNumber": 2,
      "firebaseUrl": "https://firebasestorage.googleapis.com/v0/b/pdfstudy-909ca.firebasestorage.app/o/documents%2F56%2Fpage_2.png?alt=media&token=496ed478-e4e0-4384-80ae-badad9f32e34"
    },
    {
      "pageNumber": 3,
      "firebaseUrl": "https://firebasestorage.googleapis.com/v0/b/pdfstudy-909ca.firebasestorage.app/o/documents%2F56%2Fpage_3.png?alt=media&token=015cda32-0dda-4606-beef-24b0acf29f51"
    },
    {
      "pageNumber": 4,
      "firebaseUrl": "https://firebasestorage.googleapis.com/v0/b/pdfstudy-909ca.firebasestorage.app/o/documents%2F56%2Fpage_4.png?alt=media&token=9ccfd610-c68e-4201-a87e-4b106bf0182d"
    },
    {
      "pageNumber": 5,
      "firebaseUrl": "https://firebasestorage.googleapis.com/v0/b/pdfstudy-909ca.firebasestorage.app/o/documents%2F56%2Fpage_5.png?alt=media&token=dfce6dee-c37f-460e-8021-e39433dedcdb"
    },
    {
      "pageNumber": 6,
      "firebaseUrl": "https://firebasestorage.googleapis.com/v0/b/pdfstudy-909ca.firebasestorage.app/o/documents%2F56%2Fpage_6.png?alt=media&token=76f0329a-f3c3-48b5-9116-d20dcb314ad8"
    },
    {
      "pageNumber": 7,
      "firebaseUrl": "https://firebasestorage.googleapis.com/v0/b/pdfstudy-909ca.firebasestorage.app/o/documents%2F56%2Fpage_7.png?alt=media&token=f5b81dce-8ded-443e-b8b8-f13994c69aaf"
    },
    {
      "pageNumber": 8,
      "firebaseUrl": "https://firebasestorage.googleapis.com/v0/b/pdfstudy-909ca.firebasestorage.app/o/documents%2F56%2Fpage_8.png?alt=media&token=42885b65-8256-49f1-a21d-6e0dc8e6ec92"
    },
    {
      "pageNumber": 9,
      "firebaseUrl": "https://firebasestorage.googleapis.com/v0/b/pdfstudy-909ca.firebasestorage.app/o/documents%2F56%2Fpage_9.png?alt=media&token=58cdd1ab-e4eb-4e31-880e-d1823a19c015"
    },
    {
      "pageNumber": 10,
      "firebaseUrl": "https://firebasestorage.googleapis.com/v0/b/pdfstudy-909ca.firebasestorage.app/o/documents%2F56%2Fpage_10.png?alt=media&token=c0dba251-296f-4478-b27d-ac923f8aff6f"
    },
    {
      "pageNumber": 11,
      "firebaseUrl": "https://firebasestorage.googleapis.com/v0/b/pdfstudy-909ca.firebasestorage.app/o/documents%2F56%2Fpage_11.png?alt=media&token=4207aa5a-414b-4438-a112-405f4d2f395c"
    },
    {
      "pageNumber": 12,
      "firebaseUrl": "https://firebasestorage.googleapis.com/v0/b/pdfstudy-909ca.firebasestorage.app/o/documents%2F56%2Fpage_12.png?alt=media&token=e929feac-d2b7-48b3-8c6e-8a77ad5cc21c"
    },
    {
      "pageNumber": 13,
      "firebaseUrl": "https://firebasestorage.googleapis.com/v0/b/pdfstudy-909ca.firebasestorage.app/o/documents%2F56%2Fpage_13.png?alt=media&token=944caefd-7093-4d03-ac46-8800be74e76d"
    },
    {
      "pageNumber": 14,
      "firebaseUrl": "https://firebasestorage.googleapis.com/v0/b/pdfstudy-909ca.firebasestorage.app/o/documents%2F56%2Fpage_14.png?alt=media&token=ff448461-32bd-4397-989d-7a5d6d6578d3"
    },
    {
      "pageNumber": 15,
      "firebaseUrl": "https://firebasestorage.googleapis.com/v0/b/pdfstudy-909ca.firebasestorage.app/o/documents%2F56%2Fpage_15.png?alt=media&token=8aee87c4-1608-4a50-9630-ef5d5d301b65"
    },
    {
      "pageNumber": 16,
      "firebaseUrl": "https://firebasestorage.googleapis.com/v0/b/pdfstudy-909ca.firebasestorage.app/o/documents%2F56%2Fpage_16.png?alt=media&token=ffd4390f-e998-4c3b-b5de-59421d708447"
    },
    {
      "pageNumber": 17,
      "firebaseUrl": "https://firebasestorage.googleapis.com/v0/b/pdfstudy-909ca.firebasestorage.app/o/documents%2F56%2Fpage_17.png?alt=media&token=0f17928b-e2e6-489e-96f8-e75a127d51e8"
    },
    {
      "pageNumber": 18,
      "firebaseUrl": "https://firebasestorage.googleapis.com/v0/b/pdfstudy-909ca.firebasestorage.app/o/documents%2F56%2Fpage_18.png?alt=media&token=60959011-8568-4a5d-aeb7-6f81337d0b8a"
    },
    {
      "pageNumber": 19,
      "firebaseUrl": "https://firebasestorage.googleapis.com/v0/b/pdfstudy-909ca.firebasestorage.app/o/documents%2F56%2Fpage_19.png?alt=media&token=4f173371-1037-4c4b-a24d-e5edd8667048"
    },
    {
      "pageNumber": 20,
      "firebaseUrl": "https://firebasestorage.googleapis.com/v0/b/pdfstudy-909ca.firebasestorage.app/o/documents%2F56%2Fpage_20.png?alt=media&token=08671238-a689-45a9-beca-71111a19d917"
    },
    {
      "pageNumber": 21,
      "firebaseUrl": "https://firebasestorage.googleapis.com/v0/b/pdfstudy-909ca.firebasestorage.app/o/documents%2F56%2Fpage_21.png?alt=media&token=7a58e31a-a83e-445c-a032-a370c872600a"
    },
    {
      "pageNumber": 22,
      "firebaseUrl": "https://firebasestorage.googleapis.com/v0/b/pdfstudy-909ca.firebasestorage.app/o/documents%2F56%2Fpage_22.png?alt=media&token=0b043ceb-ca0b-417e-ae8b-1ee5ce9eb330"
    },
    {
      "pageNumber": 23,
      "firebaseUrl": "https://firebasestorage.googleapis.com/v0/b/pdfstudy-909ca.firebasestorage.app/o/documents%2F56%2Fpage_23.png?alt=media&token=da4f3d13-20d2-4ffd-920e-e0777a7a0df6"
    },
    {
      "pageNumber": 24,
      "firebaseUrl": "https://firebasestorage.googleapis.com/v0/b/pdfstudy-909ca.firebasestorage.app/o/documents%2F56%2Fpage_24.png?alt=media&token=5e6a21f6-3ec8-4e6a-87f9-61074bbe84ca"
    },
    {
      "pageNumber": 25,
      "firebaseUrl": "https://firebasestorage.googleapis.com/v0/b/pdfstudy-909ca.firebasestorage.app/o/documents%2F56%2Fpage_25.png?alt=media&token=cc3f2a52-ce0f-497d-a084-35c647f0ca03"
    },
    {
      "pageNumber": 26,
      "firebaseUrl": "https://firebasestorage.googleapis.com/v0/b/pdfstudy-909ca.firebasestorage.app/o/documents%2F56%2Fpage_26.png?alt=media&token=e03cba0e-a7ba-4373-889c-be54f63fc8aa"
    },
    {
      "pageNumber": 27,
      "firebaseUrl": "https://firebasestorage.googleapis.com/v0/b/pdfstudy-909ca.firebasestorage.app/o/documents%2F56%2Fpage_27.png?alt=media&token=500e0835-bd88-40f6-a762-e2cfaec7bb61"
    },
    {
      "pageNumber": 28,
      "firebaseUrl": "https://firebasestorage.googleapis.com/v0/b/pdfstudy-909ca.firebasestorage.app/o/documents%2F56%2Fpage_28.png?alt=media&token=b6d5bcba-51d0-4da5-b1bb-dfd3c453aed9"
    },
    {
      "pageNumber": 29,
      "firebaseUrl": "https://firebasestorage.googleapis.com/v0/b/pdfstudy-909ca.firebasestorage.app/o/documents%2F56%2Fpage_29.png?alt=media&token=77cb8e6a-e7b7-4d81-b48c-e8a21d63dcac"
    },
    {
      "pageNumber": 30,
      "firebaseUrl": "https://firebasestorage.googleapis.com/v0/b/pdfstudy-909ca.firebasestorage.app/o/documents%2F56%2Fpage_30.png?alt=media&token=ff0c5152-f699-40a6-9237-22edcb48f4f1"
    },
    {
      "pageNumber": 31,
      "firebaseUrl": "https://firebasestorage.googleapis.com/v0/b/pdfstudy-909ca.firebasestorage.app/o/documents%2F56%2Fpage_31.png?alt=media&token=34add5fc-6297-414b-af29-b61d00d8cf32"
    },
    {
      "pageNumber": 32,
      "firebaseUrl": "https://firebasestorage.googleapis.com/v0/b/pdfstudy-909ca.firebasestorage.app/o/documents%2F56%2Fpage_32.png?alt=media&token=c305323c-7406-48b8-b4c8-59038320c336"
    },
    {
      "pageNumber": 33,
      "firebaseUrl": "https://firebasestorage.googleapis.com/v0/b/pdfstudy-909ca.firebasestorage.app/o/documents%2F56%2Fpage_33.png?alt=media&token=d06a6b57-2b19-42fd-b70f-a8b89cdeea78"
    },
    {
      "pageNumber": 34,
      "firebaseUrl": "https://firebasestorage.googleapis.com/v0/b/pdfstudy-909ca.firebasestorage.app/o/documents%2F56%2Fpage_34.png?alt=media&token=6421890a-dfe8-4bbd-9b25-84e8797bb938"
    },
    {
      "pageNumber": 35,
      "firebaseUrl": "https://firebasestorage.googleapis.com/v0/b/pdfstudy-909ca.firebasestorage.app/o/documents%2F56%2Fpage_35.png?alt=media&token=72a2055a-e51a-4166-82cb-b8c59d1d908c"
    },
    {
      "pageNumber": 36,
      "firebaseUrl": "https://firebasestorage.googleapis.com/v0/b/pdfstudy-909ca.firebasestorage.app/o/documents%2F56%2Fpage_36.png?alt=media&token=65a528b7-680a-425c-8626-e5a46fa9bc4e"
    },
    {
      "pageNumber": 37,
      "firebaseUrl": "https://firebasestorage.googleapis.com/v0/b/pdfstudy-909ca.firebasestorage.app/o/documents%2F56%2Fpage_37.png?alt=media&token=d470c799-6cfc-4880-8b0e-f3702ebcebc6"
    },
    {
      "pageNumber": 38,
      "firebaseUrl": "https://firebasestorage.googleapis.com/v0/b/pdfstudy-909ca.firebasestorage.app/o/documents%2F56%2Fpage_38.png?alt=media&token=340f0f0a-5507-4812-93df-5e3883dfc2cf"
    },
    {
      "pageNumber": 39,
      "firebaseUrl": "https://firebasestorage.googleapis.com/v0/b/pdfstudy-909ca.firebasestorage.app/o/documents%2F56%2Fpage_39.png?alt=media&token=25393040-ab67-43b8-9a0c-0adbee0ba75a"
    },
    {
      "pageNumber": 40,
      "firebaseUrl": "https://firebasestorage.googleapis.com/v0/b/pdfstudy-909ca.firebasestorage.app/o/documents%2F56%2Fpage_40.png?alt=media&token=76abf539-3e58-4b21-aeea-8e04cf0cae23"
    },
    {
      "pageNumber": 41,
      "firebaseUrl": "https://firebasestorage.googleapis.com/v0/b/pdfstudy-909ca.firebasestorage.app/o/documents%2F56%2Fpage_41.png?alt=media&token=51cb5b1f-dd23-4458-ab80-528219fefd57"
    },
    {
      "pageNumber": 42,
      "firebaseUrl": "https://firebasestorage.googleapis.com/v0/b/pdfstudy-909ca.firebasestorage.app/o/documents%2F56%2Fpage_42.png?alt=media&token=04be9ef6-127c-4a9a-a0e8-178d06f9c377"
    },
    {
      "pageNumber": 43,
      "firebaseUrl": "https://firebasestorage.googleapis.com/v0/b/pdfstudy-909ca.firebasestorage.app/o/documents%2F56%2Fpage_43.png?alt=media&token=1b3e38db-f9a7-4f2d-acc0-6742d7068c66"
    },
    {
      "pageNumber": 44,
      "firebaseUrl": "https://firebasestorage.googleapis.com/v0/b/pdfstudy-909ca.firebasestorage.app/o/documents%2F56%2Fpage_44.png?alt=media&token=07aecf1a-dfac-4017-8d43-971c8820f8de"
    },
    {
      "pageNumber": 45,
      "firebaseUrl": "https://firebasestorage.googleapis.com/v0/b/pdfstudy-909ca.firebasestorage.app/o/documents%2F56%2Fpage_45.png?alt=media&token=621a1abb-d8e5-490e-a43a-201fb7093f19"
    },
    {
      "pageNumber": 46,
      "firebaseUrl": "https://firebasestorage.googleapis.com/v0/b/pdfstudy-909ca.firebasestorage.app/o/documents%2F56%2Fpage_46.png?alt=media&token=0e0de6e4-9143-4328-b094-c1361e4c3a9e"
    },
    {
      "pageNumber": 47,
      "firebaseUrl": "https://firebasestorage.googleapis.com/v0/b/pdfstudy-909ca.firebasestorage.app/o/documents%2F56%2Fpage_47.png?alt=media&token=e33518ef-b39c-4d17-bfc2-55c206dc7512"
    },
    {
      "pageNumber": 48,
      "firebaseUrl": "https://firebasestorage.googleapis.com/v0/b/pdfstudy-909ca.firebasestorage.app/o/documents%2F56%2Fpage_48.png?alt=media&token=92cae02d-46ff-47a5-bbd5-6aeb490c03cc"
    },
    {
      "pageNumber": 49,
      "firebaseUrl": "https://firebasestorage.googleapis.com/v0/b/pdfstudy-909ca.firebasestorage.app/o/documents%2F56%2Fpage_49.png?alt=media&token=cbdf1405-614a-4f18-abb4-014f91ea20ae"
    },
    {
      "pageNumber": 50,
      "firebaseUrl": "https://firebasestorage.googleapis.com/v0/b/pdfstudy-909ca.firebasestorage.app/o/documents%2F56%2Fpage_50.png?alt=media&token=3e914acf-d07e-47b7-b162-9c6a2156abf8"
    },
    {
      "pageNumber": 51,
      "firebaseUrl": "https://firebasestorage.googleapis.com/v0/b/pdfstudy-909ca.firebasestorage.app/o/documents%2F56%2Fpage_51.png?alt=media&token=2223e0be-3898-407c-a551-669a4ad67012"
    },
    {
      "pageNumber": 52,
      "firebaseUrl": "https://firebasestorage.googleapis.com/v0/b/pdfstudy-909ca.firebasestorage.app/o/documents%2F56%2Fpage_52.png?alt=media&token=ebb5cdab-73b4-456c-80a8-8a5b71f84193"
    },
    {
      "pageNumber": 53,
      "firebaseUrl": "https://firebasestorage.googleapis.com/v0/b/pdfstudy-909ca.firebasestorage.app/o/documents%2F56%2Fpage_53.png?alt=media&token=f4f0ee22-bd6d-4930-81b9-0baae23f2ac2"
    },
    {
      "pageNumber": 54,
      "firebaseUrl": "https://firebasestorage.googleapis.com/v0/b/pdfstudy-909ca.firebasestorage.app/o/documents%2F56%2Fpage_54.png?alt=media&token=982d6067-efef-42cb-8372-7fc0e15925a0"
    },
    {
      "pageNumber": 55,
      "firebaseUrl": "https://firebasestorage.googleapis.com/v0/b/pdfstudy-909ca.firebasestorage.app/o/documents%2F56%2Fpage_55.png?alt=media&token=d2712307-6022-4734-bf48-d9c1c2ae8161"
    },
    {
      "pageNumber": 56,
      "firebaseUrl": "https://firebasestorage.googleapis.com/v0/b/pdfstudy-909ca.firebasestorage.app/o/documents%2F56%2Fpage_56.png?alt=media&token=4952b471-17d4-422e-836e-dfce90820105"
    },
    {
      "pageNumber": 57,
      "firebaseUrl": "https://firebasestorage.googleapis.com/v0/b/pdfstudy-909ca.firebasestorage.app/o/documents%2F56%2Fpage_57.png?alt=media&token=992c7e28-875e-4306-9e64-fc5f4783d0c5"
    },
    {
      "pageNumber": 58,
      "firebaseUrl": "https://firebasestorage.googleapis.com/v0/b/pdfstudy-909ca.firebasestorage.app/o/documents%2F56%2Fpage_58.png?alt=media&token=c1f79487-bf46-46c4-90b1-ec68eb179d6a"
    },
    {
      "pageNumber": 59,
      "firebaseUrl": "https://firebasestorage.googleapis.com/v0/b/pdfstudy-909ca.firebasestorage.app/o/documents%2F56%2Fpage_59.png?alt=media&token=c42e7e23-8355-4bf1-bbc8-c24dc2a9c924"
    },
    {
      "pageNumber": 60,
      "firebaseUrl": "https://firebasestorage.googleapis.com/v0/b/pdfstudy-909ca.firebasestorage.app/o/documents%2F56%2Fpage_60.png?alt=media&token=b8037e5b-eaf3-41d4-b8fe-5af0f838d37b"
    },
    {
      "pageNumber": 61,
      "firebaseUrl": "https://firebasestorage.googleapis.com/v0/b/pdfstudy-909ca.firebasestorage.app/o/documents%2F56%2Fpage_61.png?alt=media&token=1d857978-6195-480a-891b-449927129979"
    },
    {
      "pageNumber": 62,
      "firebaseUrl": "https://firebasestorage.googleapis.com/v0/b/pdfstudy-909ca.firebasestorage.app/o/documents%2F56%2Fpage_62.png?alt=media&token=d40359b5-cb2d-4a99-923b-af1d6d8efe1a"
    },
    {
      "pageNumber": 63,
      "firebaseUrl": "https://firebasestorage.googleapis.com/v0/b/pdfstudy-909ca.firebasestorage.app/o/documents%2F56%2Fpage_63.png?alt=media&token=2e4d5321-5866-47e0-9d65-eeb87620ee33"
    },
    {
      "pageNumber": 64,
      "firebaseUrl": "https://firebasestorage.googleapis.com/v0/b/pdfstudy-909ca.firebasestorage.app/o/documents%2F56%2Fpage_64.png?alt=media&token=4a7485d8-4bb9-4215-a873-0b5ea307a512"
    },
    {
      "pageNumber": 65,
      "firebaseUrl": "https://firebasestorage.googleapis.com/v0/b/pdfstudy-909ca.firebasestorage.app/o/documents%2F56%2Fpage_65.png?alt=media&token=2bff18ba-e2e3-492f-b5b7-3fe06f69371e"
    },
    {
      "pageNumber": 66,
      "firebaseUrl": "https://firebasestorage.googleapis.com/v0/b/pdfstudy-909ca.firebasestorage.app/o/documents%2F56%2Fpage_66.png?alt=media&token=8568cba5-d354-4aa6-a673-8a0b66ba6226"
    },
    {
      "pageNumber": 67,
      "firebaseUrl": "https://firebasestorage.googleapis.com/v0/b/pdfstudy-909ca.firebasestorage.app/o/documents%2F56%2Fpage_67.png?alt=media&token=ae2f2989-c39b-4c1b-b749-f25e4b38b3d7"
    },
    {
      "pageNumber": 68,
      "firebaseUrl": "https://firebasestorage.googleapis.com/v0/b/pdfstudy-909ca.firebasestorage.app/o/documents%2F56%2Fpage_68.png?alt=media&token=be13384e-00e3-4ad8-b6a9-d1fe295e387b"
    },
    {
      "pageNumber": 69,
      "firebaseUrl": "https://firebasestorage.googleapis.com/v0/b/pdfstudy-909ca.firebasestorage.app/o/documents%2F56%2Fpage_69.png?alt=media&token=0719a462-19e1-4c46-ae69-5da6507163e4"
    },
    {
      "pageNumber": 70,
      "firebaseUrl": "https://firebasestorage.googleapis.com/v0/b/pdfstudy-909ca.firebasestorage.app/o/documents%2F56%2Fpage_70.png?alt=media&token=c421386e-986b-4b76-9422-306869f4993e"
    },
    {
      "pageNumber": 71,
      "firebaseUrl": "https://firebasestorage.googleapis.com/v0/b/pdfstudy-909ca.firebasestorage.app/o/documents%2F56%2Fpage_71.png?alt=media&token=45b8339a-191e-4437-beef-1eabd3c31fc5"
    },
    {
      "pageNumber": 72,
      "firebaseUrl": "https://firebasestorage.googleapis.com/v0/b/pdfstudy-909ca.firebasestorage.app/o/documents%2F56%2Fpage_72.png?alt=media&token=bf0aeea9-e0e3-43d1-b938-4ab848ee4c28"
    },
    {
      "pageNumber": 73,
      "firebaseUrl": "https://firebasestorage.googleapis.com/v0/b/pdfstudy-909ca.firebasestorage.app/o/documents%2F56%2Fpage_73.png?alt=media&token=07b0f49f-340c-4cc3-a70b-2b03c86c45cb"
    },
    {
      "pageNumber": 74,
      "firebaseUrl": "https://firebasestorage.googleapis.com/v0/b/pdfstudy-909ca.firebasestorage.app/o/documents%2F56%2Fpage_74.png?alt=media&token=ad77866e-f247-44c5-8056-ee13ba22a7c7"
    },
    {
      "pageNumber": 75,
      "firebaseUrl": "https://firebasestorage.googleapis.com/v0/b/pdfstudy-909ca.firebasestorage.app/o/documents%2F56%2Fpage_75.png?alt=media&token=f237919b-753f-440c-b139-20dcc6f2fbd3"
    },
    {
      "pageNumber": 76,
      "firebaseUrl": "https://firebasestorage.googleapis.com/v0/b/pdfstudy-909ca.firebasestorage.app/o/documents%2F56%2Fpage_76.png?alt=media&token=997b511b-fba8-46c8-998b-3de82d30e539"
    },
    {
      "pageNumber": 77,
      "firebaseUrl": "https://firebasestorage.googleapis.com/v0/b/pdfstudy-909ca.firebasestorage.app/o/documents%2F56%2Fpage_77.png?alt=media&token=247b300f-9568-4815-bf5c-9d72712e83f9"
    },
    {
      "pageNumber": 78,
      "firebaseUrl": "https://firebasestorage.googleapis.com/v0/b/pdfstudy-909ca.firebasestorage.app/o/documents%2F56%2Fpage_78.png?alt=media&token=247ddaba-c95c-47dd-baa6-cedb628f90b0"
    },
    {
      "pageNumber": 79,
      "firebaseUrl": "https://firebasestorage.googleapis.com/v0/b/pdfstudy-909ca.firebasestorage.app/o/documents%2F56%2Fpage_79.png?alt=media&token=b60c0587-4105-46aa-b8b8-7e4205d0179b"
    },
    {
      "pageNumber": 80,
      "firebaseUrl": "https://firebasestorage.googleapis.com/v0/b/pdfstudy-909ca.firebasestorage.app/o/documents%2F56%2Fpage_80.png?alt=media&token=c5af1afa-e194-4f82-bc45-2e322c64fe26"
    },
    {
      "pageNumber": 81,
      "firebaseUrl": "https://firebasestorage.googleapis.com/v0/b/pdfstudy-909ca.firebasestorage.app/o/documents%2F56%2Fpage_81.png?alt=media&token=abf525ca-79fc-47be-9b4b-e65fa0c2d969"
    },
    {
      "pageNumber": 82,
      "firebaseUrl": "https://firebasestorage.googleapis.com/v0/b/pdfstudy-909ca.firebasestorage.app/o/documents%2F56%2Fpage_82.png?alt=media&token=fead5f77-7b17-437b-876d-fdfe8f8648c2"
    },
    {
      "pageNumber": 83,
      "firebaseUrl": "https://firebasestorage.googleapis.com/v0/b/pdfstudy-909ca.firebasestorage.app/o/documents%2F56%2Fpage_83.png?alt=media&token=55200347-4f92-420c-a1a1-6c2387ffb968"
    },
    {
      "pageNumber": 84,
      "firebaseUrl": "https://firebasestorage.googleapis.com/v0/b/pdfstudy-909ca.firebasestorage.app/o/documents%2F56%2Fpage_84.png?alt=media&token=7aaebaae-aabe-4756-ba77-00d982cac0b4"
    },
    {
      "pageNumber": 85,
      "firebaseUrl": "https://firebasestorage.googleapis.com/v0/b/pdfstudy-909ca.firebasestorage.app/o/documents%2F56%2Fpage_85.png?alt=media&token=f17d58e3-2bfc-43ff-8ad0-5cad0e6d1aae"
    },
    {
      "pageNumber": 86,
      "firebaseUrl": "https://firebasestorage.googleapis.com/v0/b/pdfstudy-909ca.firebasestorage.app/o/documents%2F56%2Fpage_86.png?alt=media&token=62b2866f-3af3-4f07-8bed-cf7bed08943d"
    },
    {
      "pageNumber": 87,
      "firebaseUrl": "https://firebasestorage.googleapis.com/v0/b/pdfstudy-909ca.firebasestorage.app/o/documents%2F56%2Fpage_87.png?alt=media&token=d3aad6c3-c30f-4aca-9e41-68be99f452b8"
    },
    {
      "pageNumber": 88,
      "firebaseUrl": "https://firebasestorage.googleapis.com/v0/b/pdfstudy-909ca.firebasestorage.app/o/documents%2F56%2Fpage_88.png?alt=media&token=4ed02bd2-d070-4843-9197-9039eac23d1f"
    },
    {
      "pageNumber": 89,
      "firebaseUrl": "https://firebasestorage.googleapis.com/v0/b/pdfstudy-909ca.firebasestorage.app/o/documents%2F56%2Fpage_89.png?alt=media&token=117109b2-683c-4c35-bc43-897f865b6032"
    },
    {
      "pageNumber": 90,
      "firebaseUrl": "https://firebasestorage.googleapis.com/v0/b/pdfstudy-909ca.firebasestorage.app/o/documents%2F56%2Fpage_90.png?alt=media&token=c7089427-83a5-4fa5-a3cb-d11507b82742"
    },
    {
      "pageNumber": 91,
      "firebaseUrl": "https://firebasestorage.googleapis.com/v0/b/pdfstudy-909ca.firebasestorage.app/o/documents%2F56%2Fpage_91.png?alt=media&token=4ed02514-7910-485d-994d-388c231da909"
    },
    {
      "pageNumber": 92,
      "firebaseUrl": "https://firebasestorage.googleapis.com/v0/b/pdfstudy-909ca.firebasestorage.app/o/documents%2F56%2Fpage_92.png?alt=media&token=ffc29ada-c749-4e11-88c4-d641e6dd5305"
    },
    {
      "pageNumber": 93,
      "firebaseUrl": "https://firebasestorage.googleapis.com/v0/b/pdfstudy-909ca.firebasestorage.app/o/documents%2F56%2Fpage_93.png?alt=media&token=18e999d5-6db0-4a02-907d-d667e9e0d6ed"
    },
    {
      "pageNumber": 94,
      "firebaseUrl": "https://firebasestorage.googleapis.com/v0/b/pdfstudy-909ca.firebasestorage.app/o/documents%2F56%2Fpage_94.png?alt=media&token=86b0523c-650c-479f-90eb-321bc9a75bf0"
    },
    {
      "pageNumber": 95,
      "firebaseUrl": "https://firebasestorage.googleapis.com/v0/b/pdfstudy-909ca.firebasestorage.app/o/documents%2F56%2Fpage_95.png?alt=media&token=e3a5b7d9-2cb2-4f9c-8ef9-ad55a9779202"
    },
    {
      "pageNumber": 96,
      "firebaseUrl": "https://firebasestorage.googleapis.com/v0/b/pdfstudy-909ca.firebasestorage.app/o/documents%2F56%2Fpage_96.png?alt=media&token=20a394f0-7fa6-4bfc-bddb-de349f08b40b"
    },
    {
      "pageNumber": 97,
      "firebaseUrl": "https://firebasestorage.googleapis.com/v0/b/pdfstudy-909ca.firebasestorage.app/o/documents%2F56%2Fpage_97.png?alt=media&token=7c2addfa-7770-4ad9-bd1d-c8e0769a163d"
    },
    {
      "pageNumber": 98,
      "firebaseUrl": "https://firebasestorage.googleapis.com/v0/b/pdfstudy-909ca.firebasestorage.app/o/documents%2F56%2Fpage_98.png?alt=media&token=20ef8b63-87d7-4687-9fa5-eab8de3c3234"
    },
    {
      "pageNumber": 99,
      "firebaseUrl": "https://firebasestorage.googleapis.com/v0/b/pdfstudy-909ca.firebasestorage.app/o/documents%2F56%2Fpage_99.png?alt=media&token=33f879b4-1737-4f36-a497-ada9b5ce7ede"
    },
    {
      "pageNumber": 100,
      "firebaseUrl": "https://firebasestorage.googleapis.com/v0/b/pdfstudy-909ca.firebasestorage.app/o/documents%2F56%2Fpage_100.png?alt=media&token=dd850289-1002-439f-bd32-f641a807536b"
    }
  ]
}